LICENSE
MANIFEST.in
README.md
classifiers.txt
setup.py
drivedroid_gen/__init__.py
drivedroid_gen_repo.egg-info/PKG-INFO
drivedroid_gen_repo.egg-info/SOURCES.txt
drivedroid_gen_repo.egg-info/dependency_links.txt
drivedroid_gen_repo.egg-info/entry_points.txt
drivedroid_gen_repo.egg-info/requires.txt
drivedroid_gen_repo.egg-info/top_level.txt