Metadata-Version: 1.1
Name: drivedroid-gen-repo
Version: 0.4.2
Summary: Generator for drivedroid repository files
Home-page: http://github.com/makefu/drivedroid-repo-gen
Author: Felix Richter
Author-email: github@syntax-fehler.de
License: wtfpl
Platform: UNKNOWN
Classifier: Development Status :: 3 - Alpha
